yapytf/__init__.py
yapytf/_cli.py
yapytf/_containers.py
yapytf/_genbase.py
yapytf/_generator.py
yapytf/_getter.py
yapytf/_goplat.py
yapytf/_hashigetter.py
yapytf/_pcache.py
yapytf/_public.py
yapytf/_tfrun.py
yapytf/_tfschema.py
yapytf/_tfstate.py
yapytf/helpers.py
yapytf-0.5.7.dist-info/LICENSE
yapytf-0.5.7.dist-info/METADATA
yapytf-0.5.7.dist-info/WHEEL
yapytf-0.5.7.dist-info/entry_points.txt
yapytf-0.5.7.dist-info/top_level.txt
yapytf-0.5.7.dist-info/RECORD
