Metadata-Version: 2.1
Name: yapytf
Version: 0.5.7
Summary: Yet Another Python Terraform Wrapper
Home-page: https://github.com/kshpytsya/yapytf
Author: Kyrylo Shpytsya
Author-email: kshpitsa@gmail.com
License: MIT
Platform: UNKNOWN
Classifier: Development Status :: 3 - Alpha
Classifier: Intended Audience :: Developers
Classifier: Intended Audience :: Information Technology
Classifier: Intended Audience :: System Administrators
Classifier: License :: OSI Approved :: MIT License
Classifier: Operating System :: MacOS :: MacOS X
Classifier: Operating System :: Microsoft :: Windows
Classifier: Operating System :: POSIX :: BSD :: FreeBSD
Classifier: Operating System :: POSIX :: BSD :: OpenBSD
Classifier: Operating System :: POSIX :: Linux
Classifier: Programming Language :: Python :: 3.6
Classifier: Programming Language :: Python :: 3.7
Classifier: Programming Language :: Python :: 3.8
Classifier: Topic :: System :: Systems Administration
Requires-Python: >=3.6, <3.9
Requires-Dist: click (<8,>=7.1.1)
Requires-Dist: click-log (<1,>=0.3.2)
Requires-Dist: implements (<1,>=0.1.4)
Requires-Dist: jsonschema (<4,>=3.2.0)
Requires-Dist: mypy (<1,>=0.770)
Requires-Dist: PyYAML (<6,>=5.3.1)
Requires-Dist: requests (<3,>=2.23.0)
Requires-Dist: toposort (<2,>=1.5)
Requires-Dist: tqdm (<5,>=4.45.0)
Requires-Dist: typeguard (<3,>=2.7.1)
Requires-Dist: typing-inspect (<1,>=0.5.0)
Requires-Dist: xdgappdirs (<2,>=1.4.5)
Requires-Dist: dataclasses (<1,>=0.6) ; python_version < "3.7"
